Metadata-Version: 1.2
Name: cerndb
Version: 0.1
Summary: CERNDB Support library and tools
Home-page: https://gitlab.cern.ch/db/python3-cerndb
Author: IT-DB-IA
Author-email: ignacio.coterillo.coz@cern.ch
Maintainer: Ignacio Coterillo
Maintainer-email: ignacio.coterillo.coz@cern.ch
License: GPLv3
Platform: UNKNOWN
